Metadata-Version: 2.4
Name: gav-func-test-runtime
Version: 1.1.0b5.dev1
Summary: Test package for Python Language Worker TZ support - Azure Functions Runtime V2
Author-email: "Azure Functions team at Microsoft Corp." <azurefunctions@microsoft.com>
Project-URL: Documentation, https://github.com/Azure/azure-functions-python-worker/blob/dev/azure_functions_runtime/README.md
Project-URL: Repository, https://github.com/Azure/azure-functions-python-worker
Keywords: azure,functions,azurefunctions,python,serverless,timezone,test
Classifier: Development Status :: 4 - Beta
Classifier: Programming Language :: Python
Classifier: Programming Language :: Python :: 3
Classifier: Programming Language :: Python :: 3.13
Classifier: Operating System :: Microsoft :: Windows
Classifier: Operating System :: POSIX
Classifier: Operating System :: MacOS :: MacOS X
Classifier: Environment :: Web Environment
Classifier: License :: OSI Approved :: MIT License
Classifier: Intended Audience :: Developers
Requires-Python: >=3.13
Requires-Dist: azurefunctions-extensions-base
Requires-Dist: azure-functions
Provides-Extra: dev
Requires-Dist: azure-monitor-opentelemetry; extra == "dev"
Requires-Dist: flake8==6.*; extra == "dev"
Requires-Dist: mypy; extra == "dev"
Requires-Dist: pytest; extra == "dev"
Requires-Dist: requests==2.*; extra == "dev"
Requires-Dist: coverage; extra == "dev"
Requires-Dist: grpcio~=1.70.0; extra == "dev"
Requires-Dist: grpcio-tools~=1.70.0; extra == "dev"
Requires-Dist: protobuf~=5.29.0; extra == "dev"
Requires-Dist: pytest-sugar; extra == "dev"
Requires-Dist: pytest-cov; extra == "dev"
Requires-Dist: pytest-xdist; extra == "dev"
Requires-Dist: pytest-randomly; extra == "dev"
Requires-Dist: pytest-instafail; extra == "dev"
Requires-Dist: pytest-rerunfailures; extra == "dev"
Requires-Dist: pytest-asyncio; extra == "dev"
Requires-Dist: pre-commit; extra == "dev"
Requires-Dist: invoke; extra == "dev"
Provides-Extra: test-http-v2
Requires-Dist: azurefunctions-extensions-http-fastapi==1.0.0; extra == "test-http-v2"
Requires-Dist: ujson; extra == "test-http-v2"
Requires-Dist: orjson; extra == "test-http-v2"
Provides-Extra: test-deferred-bindings
Requires-Dist: azurefunctions-extensions-bindings-blob==1.0.0; extra == "test-deferred-bindings"
Requires-Dist: azurefunctions-extensions-bindings-eventhub==1.0.0b1; extra == "test-deferred-bindings"
